README.rst
setup.py
src/easy_sanic/__init__.py
src/easy_sanic/app.py
src/easy_sanic/service.py
src/easy_sanic/settings.py
src/easy_sanic/url.py
src/easy_sanic.egg-info/PKG-INFO
src/easy_sanic.egg-info/SOURCES.txt
src/easy_sanic.egg-info/dependency_links.txt
src/easy_sanic.egg-info/not-zip-safe
src/easy_sanic.egg-info/requires.txt
src/easy_sanic.egg-info/top_level.txt
src/easy_sanic/db/__init__.py
src/easy_sanic/db/dao.py
src/easy_sanic/db/db.py
src/easy_sanic/db/init_sql_table.py
src/easy_sanic/db/orm.py
src/easy_sanic/restful/__init__.py
src/easy_sanic/restful/operation_handler.py
src/easy_sanic/tests/__init__.py
src/easy_sanic/utils/__init__.py
src/easy_sanic/utils/aio_redis.py
src/easy_sanic/utils/ascci_helper.py
src/easy_sanic/utils/jwt_helper.py
src/easy_sanic/utils/redis.py
src/easy_sanic/utils/utils.py
src/easy_sanic/views/__init__.py
src/easy_sanic/views/auth_filter.py
src/easy_sanic/views/restful_api.py
src/easy_sanic/views/user_views.py
src/easy_sanic/views/xauth.py